setup.py
EvGen.egg-info/PKG-INFO
EvGen.egg-info/SOURCES.txt
EvGen.egg-info/dependency_links.txt
EvGen.egg-info/requires.txt
EvGen.egg-info/top_level.txt
evgen/__init__.py
evgen/core.py
evgen/formats.py
evgen/utils.py
evgen/writers.py
evgen.egg-info/PKG-INFO
evgen.egg-info/SOURCES.txt
evgen.egg-info/dependency_links.txt
evgen.egg-info/requires.txt
evgen.egg-info/top_level.txt
examples/basic.py
examples/custom_sink.py
examples/directory_writer.py
examples/finance_demo.py
examples/rabbitmq.py
examples/timeseries.py
examples/timeseries_server.py
examples/timeseries_stateful.py