Metadata-Version: 1.1
Name: evgen
Version: 0.7
Summary: Comprehensive event generation framework
Home-page: https://github.com/MichalZylinski/evgen
Author: Michal Zylinski
Author-email: michal.zylinski@gmail.com
License: MIT
Platform: UNKNOWN
Classifier: Programming Language :: Python :: 2.7
Classifier: Programming Language :: Python :: 3
